rs_fast_one_hot/__init__.py
rs_fast_one_hot/rs_fast_one_hot.cp38-win_amd64.pyd
rs_fast_one_hot-0.1.1.dist-info/LICENSE
rs_fast_one_hot-0.1.1.dist-info/METADATA
rs_fast_one_hot-0.1.1.dist-info/WHEEL
rs_fast_one_hot-0.1.1.dist-info/top_level.txt
rs_fast_one_hot-0.1.1.dist-info/RECORD
