Metadata-Version: 2.1
Name: rs_fast_one_hot
Version: 0.1.1
Summary: Simple class for fast one hot encoding. Support scikit-learn transformer interface and multithreading.
Author-email: GAlexander <g.alexander.box@gmail.com>
Project-URL: Homepage, https://github.com/g-alexander/rs_fast_one_hot
Project-URL: Bug Tracker, https://github.com/g-alexander/rs_fast_one_hot/issues
Classifier: Programming Language :: Python :: 3
Classifier: License :: OSI Approved :: MIT License
Classifier: Operating System :: POSIX :: Linux
Requires-Python: <3.14.0,>=3.8
License-File: LICENSE
Requires-Dist: scikit-learn
